gait3d/__init__.py
gait3d/gaitanalysis.py
gait3d/gaitanalysis3d.py
gait3d/gaitanalysis_with_top_cam-Copy1.py
gait3d/gaitanalysis_with_top_cam.py
gait3d/utils.py
gait_analysis/__init__.py
gait_analysis/_modidx.py
gait_analysis/core.py
gait_analysis/inspect.py
gait_analysis/twoD/__init__.py
gait_analysis/twoD/cam_interfaces.py
gait_analysis/twoD/detect.py
gait_analysis/twoD/export.py
gait_analysis/twoD/preprocess.py
gait_analysis/twoD/utils.py
gait_analysis-0.0.1.dist-info/LICENSE
gait_analysis-0.0.1.dist-info/METADATA
gait_analysis-0.0.1.dist-info/WHEEL
gait_analysis-0.0.1.dist-info/entry_points.txt
gait_analysis-0.0.1.dist-info/top_level.txt
gait_analysis-0.0.1.dist-info/RECORD
